[
  {
    "length": 10,
    "width": 10,
    "height": 1,
    "orientation": "portrait",
    "price": 2.4,
    "filterID": "10.10.1"
  },
  {
    "length": 10,
    "width": 20,
    "height": 1,
    "orientation": "portrait",
    "price": 2.46,
    "filterID": "10.20.1"
  },
  {
    "length": 10,
    "width": 24,
    "height": 1,
    "orientation": "portrait",
    "price": 2.88,
    "filterID": "10.24.1"
  },
  {
    "length": 10,
    "width": 25,
    "height": 1,
    "orientation": "portrait",
    "price": 3.37,
    "filterID": "10.25.1"
  },
  {
    "length": 10,
    "width": 30,
    "height": 1,
    "orientation": "portrait",
    "price": 3.84,
    "filterID": "10.30.1"
  },
  {
    "length": 12,
    "width": 12,
    "height": 1,
    "orientation": "portrait",
    "price": 2.46,
    "filterID": "12.12.1"
  },
  {
    "length": 12,
    "width": 16,
    "height": 1,
    "orientation": "portrait",
    "price": 2.46,
    "filterID": "12.16.1"
  },
  {
    "length": 12,
    "width": 18,
    "height": 1,
    "orientation": "portrait",
    "price": 2.46,
    "filterID": "12.18.1"
  },
  {
    "length": 12,
    "width": 20,
    "height": 1,
    "orientation": "portrait",
    "price": 2.46,
    "filterID": "12.20.1"
  },
  {
    "length": 12,
    "width": 24,
    "height": 1,
    "orientation": "portrait",
    "price": 2.41,
    "filterID": "12.24.1"
  },
  {
    "length": 12,
    "width": 25,
    "height": 1,
    "orientation": "portrait",
    "price": 2.77,
    "filterID": "12.25.1"
  },
  {
    "length": 12,
    "width": 30,
    "height": 1,
    "orientation": "portrait",
    "price": 3.95,
    "filterID": "12.30.1"
  },
  {
    "length": 14,
    "width": 14,
    "height": 1,
    "orientation": "portrait",
    "price": 2.4,
    "filterID": "14.14.1"
  },
  {
    "length": 14,
    "width": 20,
    "height": 1,
    "orientation": "portrait",
    "price": 2.62,
    "filterID": "14.20.1"
  },
  {
    "length": 14,
    "width": 24,
    "height": 1,
    "orientation": "portrait",
    "price": 2.52,
    "filterID": "14.24.1"
  },
  {
    "length": 14,
    "width": 25,
    "height": 1,
    "orientation": "portrait",
    "price": 2.85,
    "filterID": "14.25.1"
  },
  {
    "length": 14,
    "width": 30,
    "height": 1,
    "orientation": "portrait",
    "price": 3.47,
    "filterID": "14.30.1"
  },
  {
    "length": 15,
    "width": 20,
    "height": 1,
    "orientation": "portrait",
    "price": 2.84,
    "filterID": "15.20.1"
  },
  {
    "length": 15,
    "width": 25,
    "height": 1,
    "orientation": "portrait",
    "price": 3.47,
    "filterID": "15.25.1"
  },
  {
    "length": 15,
    "width": 30,
    "height": 1,
    "orientation": "portrait",
    "price": 3.79,
    "filterID": "15.30.1"
  },
  {
    "length": 16,
    "width": 16,
    "height": 1,
    "orientation": "portrait",
    "price": 2.51,
    "filterID": "16.16.1"
  },
  {
    "length": 16,
    "width": 20,
    "height": 1,
    "orientation": "portrait",
    "price": 2.3,
    "filterID": "16.20.1"
  },
  {
    "length": 16,
    "width": 24,
    "height": 1,
    "orientation": "portrait",
    "price": 2.51,
    "filterID": "16.24.1"
  },
  {
    "length": 16,
    "width": 25,
    "height": 1,
    "orientation": "portrait",
    "price": 2.6,
    "filterID": "16.25.1"
  },
  {
    "length": 16,
    "width": 30,
    "height": 1,
    "orientation": "portrait",
    "price": 3.79,
    "filterID": "16.30.1"
  },
  {
    "length": 18,
    "width": 18,
    "height": 1,
    "orientation": "portrait",
    "price": 3.09,
    "filterID": "18.18.1"
  },
  {
    "length": 18,
    "width": 20,
    "height": 1,
    "orientation": "portrait",
    "price": 3.09,
    "filterID": "18.20.1"
  },
  {
    "length": 18,
    "width": 24,
    "height": 1,
    "orientation": "portrait",
    "price": 3.09,
    "filterID": "18.24.1"
  },
  {
    "length": 18,
    "width": 25,
    "height": 1,
    "orientation": "portrait",
    "price": 3.09,
    "filterID": "18.25.1"
  },
  {
    "length": 18,
    "width": 30,
    "height": 1,
    "orientation": "portrait",
    "price": 4.09,
    "filterID": "18.30.1"
  },
  {
    "length": 20,
    "width": 20,
    "height": 1,
    "orientation": "portrait",
    "price": 2.62,
    "filterID": "20.20.1"
  },
  {
    "length": 20,
    "width": 22,
    "height": 1,
    "orientation": "portrait",
    "price": 3.81,
    "filterID": "20.22.1"
  },
  {
    "length": 20,
    "width": 24,
    "height": 1,
    "orientation": "portrait",
    "price": 2.9,
    "filterID": "20.24.1"
  },
  {
    "length": 20,
    "width": 25,
    "height": 1,
    "orientation": "portrait",
    "price": 2.9,
    "filterID": "20.25.1"
  },
  {
    "length": 20,
    "width": 30,
    "height": 1,
    "orientation": "portrait",
    "price": 4.16,
    "filterID": "20.30.1"
  },
  {
    "length": 22,
    "width": 22,
    "height": 1,
    "orientation": "portrait",
    "price": 3.9,
    "filterID": "22.22.1"
  },
  {
    "length": 24,
    "width": 24,
    "height": 1,
    "orientation": "portrait",
    "price": 3.12,
    "filterID": "24.24.1"
  },
  {
    "length": 24,
    "width": 30,
    "height": 1,
    "orientation": "portrait",
    "price": 4.41,
    "filterID": "24.30.1"
  },
  {
    "length": 25,
    "width": 25,
    "height": 1,
    "orientation": "portrait",
    "price": 4.16,
    "filterID": "25.25.1"
  }
]